Metadata-Version: 2.1
Name: dl-plus-extractor-un1def-wasdtv
Version: 0.5.0
Summary: A dl-plus extractor plugin for WASD.TV streaming platform
Home-page: https://github.com/un-def/dl-plus-extractor-un1def-wasdtv
Author: un.def
Author-email: me@undef.im
License: MIT
Platform: UNKNOWN
Requires-Python: >=3.6
Provides-Extra: dl_plus
Requires-Dist: dl-plus (>=0.3) ; extra == 'dl_plus'
